mxmul_pkg/__init__.py
mxmul_pkg/tommytime04242.py
tommytime04242-0.1.0.dist-info/LICENSE
tommytime04242-0.1.0.dist-info/METADATA
tommytime04242-0.1.0.dist-info/WHEEL
tommytime04242-0.1.0.dist-info/top_level.txt
tommytime04242-0.1.0.dist-info/RECORD
