Metadata-Version: 2.1
Name: tommytime04242
Version: 0.1.0
Summary: # Tommy的时间！
